{
  "users": {
    "Marcos": {
      "passwordHash": "$2a$10$B5pwtjLwa6HGdLkTeTjyKeYLe3sy1XslzEhq5UI02o4wXxc/.BS1q"
    },
    "Andrea": {
      "passwordHash": "$2a$10$DRJ0cPo6SuCreIjMSiOsGO6k1/crjdhL7e0ep7Mxc/qVqtxprv5/2"
    },
    "Sara Cambero": {
      "passwordHash": "$2a$10$oqF30NB4gL9iEH6sg3XpJ.1NlR73MftLT6MicAm51SWOaoA4.8pY."
    },
    "Mario": {
      "passwordHash": "$2a$10$C8/jwRW2QGEd0mZunP06T.mr.8cxAf5u3OtbW09mC5LlbnIXQMCDu"
    },
    "Sara Chacon": {
      "passwordHash": "$2a$10$lgzH47O1iTrwQY0q1YKAAOA/A4WZaAm70UgTdpwV2cbhvszMPks9W"
    },
    "Nuno": {
      "passwordHash": "$2a$10$Y0qXruSdzZA6BB2XrMPLueK2OJ6EgDl6I7AcVuMVX574vGxen25bG"
    },
    "Lucia": {
      "passwordHash": "$2a$10$2kTuI1GPUDFdRFBCysUeze9Tn0ectCnHou46Dg60KyW1nxllmH7re"
    },
    "Jimena": {
      "passwordHash": "$2a$10$0l4/Ye6u85X6XhNX3q5P7.iFLV/GER6GYlxp2KlWrmmHzLeJScAqC"
    },
    "Eva": {
      "passwordHash": "$2a$10$tEXVxFI3OA1bOqta325d9u6YYC1.IU4.XQyj01DeuRCGUfqV4MVtK"
    },
    "Sara Chimeno": {
      "passwordHash": "$2a$10$0YU23SojhpG8NB653/Q3uuFixEkjWRlLfvumVzS.ckLwWvlE7xoXK"
    },
    "Aaron": {
      "passwordHash": "$2a$10$eSZFAKD7Qihi7tXLIDpfPOjFSavMowC6vRg.rDS6L1O05vSMq88c2"
    }
  },
  "calendario": [],
  "eventos": [],
  "capsulasTiempo": [],
  "notifications": []
}